README.rst
dsargparse.py
setup.py
dsargparse.egg-info/PKG-INFO
dsargparse.egg-info/SOURCES.txt
dsargparse.egg-info/dependency_links.txt
dsargparse.egg-info/top_level.txt