Metadata-Version: 1.1
Name: dsargparse
Version: 0.3.1
Summary: dsargparse: docstring based argparse.
